bybit_mystery/__init__.py
bybit_mystery/_resources.py
bybit_mystery/main.py
bybit_mystery_client_deskent-0.0.1.data/scripts/main.py
bybit_mystery_client_deskent-0.0.1.dist-info/LICENSE.txt
bybit_mystery_client_deskent-0.0.1.dist-info/METADATA
bybit_mystery_client_deskent-0.0.1.dist-info/WHEEL
bybit_mystery_client_deskent-0.0.1.dist-info/top_level.txt
bybit_mystery_client_deskent-0.0.1.dist-info/RECORD
