Metadata-Version: 2.1
Name: bybit-mystery-client-deskent
Version: 0.0.1
Summary: Bybit Mystery
Home-page: https://github.com/Deskent/bybit-mystery
Author: Deskent
Author-email: battenetciz@gmail.com
Classifier: License :: OSI Approved :: MIT License
Classifier: Programming Language :: Python
Classifier: Programming Language :: Python :: 3
Classifier: Programming Language :: Python :: 3 :: Only
Classifier: Programming Language :: Python :: 3.7
Classifier: Programming Language :: Python :: 3.8
Classifier: Programming Language :: Python :: 3.9
Classifier: Programming Language :: Python :: 3.10
Classifier: Operating System :: OS Independent
Requires-Python: >=3.7
License-File: LICENSE.txt
Requires-Dist: aiohttp (==3.8.1)
Requires-Dist: python-dotenv (==0.19.2)
Requires-Dist: selenium-wire (==4.6.2)
Requires-Dist: selenium (~=4.1.5)
Requires-Dist: webdriver-manager (==3.7.0)
Requires-Dist: myloguru-deskent (~=0.0.9)
